{
  "name": "Hoshiguma_voicepack",
  "vobank": "Hoshiguma_soundbank",
  "baseVoice": "f_bear02",
  "stop_event": "Hoshiguma_Stop_All",
  "gender": "Female",
  "dark_phrases": {
    "acquired_object": ["Play_Hoshiguma_CN_034"],
    "acquired_vip": ["Play_Hoshiguma_CN_003"],
    "airstrike_them": ["Play_Hoshiguma_CN_030"],
    "airstrike_us": ["Play_Hoshiguma_CN_024"],
    "ammo_gone_ac10": ["Play_Hoshiguma_CN_031"],
    "ammo_gone_ac2": ["Play_Hoshiguma_CN_031"],
    "ammo_gone_ac20": ["Play_Hoshiguma_CN_031"],
    "ammo_gone_ac5": ["Play_Hoshiguma_CN_031"],
    "ammo_gone_flamer": ["Play_Hoshiguma_CN_031"],
    "ammo_gone_generic": ["Play_Hoshiguma_CN_031"],
    "ammo_gone_guass": ["Play_Hoshiguma_CN_031"],
    "ammo_gone_lrm": ["Play_Hoshiguma_CN_031"],
    "ammo_gone_mg": ["Play_Hoshiguma_CN_031"],
    "ammo_gone_multiple": ["Play_Hoshiguma_CN_031"],
    "ammo_gone_srm": ["Play_Hoshiguma_CN_031"],
    "artillery_them": ["Play_Hoshiguma_CN_030"],
    "artillery_us": ["Play_Hoshiguma_CN_024"],
    "building_destroyed": ["Play_Hoshiguma_CN_012"],
    "chatter_arid": ["Play_Hoshiguma_CN_005"],
    "chatter_frozen": ["Play_Hoshiguma_CN_017"],
    "chatter_jungle": ["Play_Hoshiguma_CN_010"],
    "chatter_martian": ["Play_Hoshiguma_CN_019"],
    "chatter_urban": ["Play_Hoshiguma_CN_020"],
    "chatter_verdant": ["Play_Hoshiguma_CN_018"],
    "chatter": ["Play_Hoshiguma_CN_036"],
    "chosen": ["Play_Hoshiguma_CN_042"],
    "done": ["Play_Hoshiguma_CN_013"],
    "drone_deployed": ["Play_Hoshiguma_CN_002"],
    "enemy_critical": ["Play_Hoshiguma_CN_025"],
    "enemy_kill": ["Play_Hoshiguma_CN_026"],
    "enemy_presence_first": ["Play_Hoshiguma_CN_024"],
    "enemy_presence_more": ["Play_Hoshiguma_CN_026"],
    "enemy_vehicle_kill": ["Play_Hoshiguma_CN_026"],
    "friendly_destroyed": ["Play_Hoshiguma_CN_032"],
    "friendly_killed": ["Play_Hoshiguma_CN_031"],
    "generic": ["Play_Hoshiguma_CN_001"],
    "hit_barely": ["Play_Hoshiguma_CN_033"],
    "hit_critical": ["Play_Hoshiguma_CN_031"],
    "hit_hard": ["Play_Hoshiguma_CN_032"],
    "hit_internal": ["Play_Hoshiguma_CN_029"],
    "jump": ["Play_Hoshiguma_CN_021"],
    "mech_down": ["Play_Hoshiguma_CN_025"],
    "mech_limping": ["Play_Hoshiguma_CN_033"],
    "mech_powerup": ["Play_Hoshiguma_CN_030"],
    "mech_up": ["Play_Hoshiguma_CN_029"],
    "move": ["Play_Hoshiguma_CN_034"],
    "overheat_shutdown": ["Play_Hoshiguma_CN_032"],
    "overheat_warning": ["Play_Hoshiguma_CN_031"],
    "pilot_death": ["Play_Hoshiguma_CN_032"],
    "pilot_demoralized": ["Play_Hoshiguma_CN_031"],
    "pilot_ejecting": ["Play_Hoshiguma_CN_032"],
    "pilot_hit": ["Play_Hoshiguma_CN_031"],
    "pilot_hurt": ["Play_Hoshiguma_CN_032"],
    "pilot_inspired": ["Play_Hoshiguma_CN_029"],
    "pilot_wakes": ["Play_Hoshiguma_CN_024"],
    "pvp_start": ["Play_Hoshiguma_CN_031"],
    "reserve": ["Play_Hoshiguma_CN_022"],
    "retreat": ["Play_Hoshiguma_CN_032"],
    "sensor_lock_onthem": ["Play_Hoshiguma_CN_024"],
    "sensor_lock_onus": ["Play_Hoshiguma_CN_030"],
    "sprint": ["Play_Hoshiguma_CN_029"],
    "support_used": ["Play_Hoshiguma_CN_030"],
    "target_alpha": ["Play_Hoshiguma_CN_025"],
    "target_dfa": ["Play_Hoshiguma_CN_027"],
    "target_fire": ["Play_Hoshiguma_CN_028"],
    "target_melee": ["Play_Hoshiguma_CN_026"],
    "target_missed": ["Play_Hoshiguma_CN_023"],
    "target_multi": ["Play_Hoshiguma_CN_028"],
    "target_rear": ["Play_Hoshiguma_CN_024"],
    "target_structure": ["Play_Hoshiguma_CN_027"],
    "turret_destroyed": ["Play_Hoshiguma_CN_026"],
    "warning_flank": ["Play_Hoshiguma_CN_031"],
    "weapon_lost_all": ["Play_Hoshiguma_CN_032"],
    "weapon_lost": ["Play_Hoshiguma_CN_031"]
  },
  "light_phrases": {
    "acquired_object": ["Play_Hoshiguma_CN_034"],
    "acquired_vip": ["Play_Hoshiguma_CN_003"],
    "airstrike_them": ["Play_Hoshiguma_CN_030"],
    "airstrike_us": ["Play_Hoshiguma_CN_024"],
    "ammo_gone_ac10": ["Play_Hoshiguma_CN_031"],
    "ammo_gone_ac2": ["Play_Hoshiguma_CN_031"],
    "ammo_gone_ac20": ["Play_Hoshiguma_CN_031"],
    "ammo_gone_ac5": ["Play_Hoshiguma_CN_031"],
    "ammo_gone_flamer": ["Play_Hoshiguma_CN_031"],
    "ammo_gone_generic": ["Play_Hoshiguma_CN_031"],
    "ammo_gone_guass": ["Play_Hoshiguma_CN_031"],
    "ammo_gone_lrm": ["Play_Hoshiguma_CN_031"],
    "ammo_gone_mg": ["Play_Hoshiguma_CN_031"],
    "ammo_gone_multiple": ["Play_Hoshiguma_CN_031"],
    "ammo_gone_srm": ["Play_Hoshiguma_CN_031"],
    "artillery_them": ["Play_Hoshiguma_CN_030"],
    "artillery_us": ["Play_Hoshiguma_CN_024"],
    "building_destroyed": ["Play_Hoshiguma_CN_012"],
    "chatter_arid": ["Play_Hoshiguma_CN_005"],
    "chatter_frozen": ["Play_Hoshiguma_CN_017"],
    "chatter_jungle": ["Play_Hoshiguma_CN_010"],
    "chatter_martian": ["Play_Hoshiguma_CN_019"],
    "chatter_urban": ["Play_Hoshiguma_CN_020"],
    "chatter_verdant": ["Play_Hoshiguma_CN_018"],
    "chatter": ["Play_Hoshiguma_CN_036"],
    "chosen": ["Play_Hoshiguma_CN_042"],
    "done": ["Play_Hoshiguma_CN_013"],
    "drone_deployed": ["Play_Hoshiguma_CN_002"],
    "enemy_critical": ["Play_Hoshiguma_CN_025"],
    "enemy_kill": ["Play_Hoshiguma_CN_026"],
    "enemy_presence_first": ["Play_Hoshiguma_CN_024"],
    "enemy_presence_more": ["Play_Hoshiguma_CN_026"],
    "enemy_vehicle_kill": ["Play_Hoshiguma_CN_026"],
    "friendly_destroyed": ["Play_Hoshiguma_CN_032"],
    "friendly_killed": ["Play_Hoshiguma_CN_031"],
    "generic": ["Play_Hoshiguma_CN_001"],
    "hit_barely": ["Play_Hoshiguma_CN_033"],
    "hit_critical": ["Play_Hoshiguma_CN_031"],
    "hit_hard": ["Play_Hoshiguma_CN_032"],
    "hit_internal": ["Play_Hoshiguma_CN_029"],
    "jump": ["Play_Hoshiguma_CN_021"],
    "mech_down": ["Play_Hoshiguma_CN_025"],
    "mech_limping": ["Play_Hoshiguma_CN_033"],
    "mech_powerup": ["Play_Hoshiguma_CN_030"],
    "mech_up": ["Play_Hoshiguma_CN_029"],
    "move": ["Play_Hoshiguma_CN_034"],
    "overheat_shutdown": ["Play_Hoshiguma_CN_032"],
    "overheat_warning": ["Play_Hoshiguma_CN_031"],
    "pilot_death": ["Play_Hoshiguma_CN_032"],
    "pilot_demoralized": ["Play_Hoshiguma_CN_031"],
    "pilot_ejecting": ["Play_Hoshiguma_CN_032"],
    "pilot_hit": ["Play_Hoshiguma_CN_031"],
    "pilot_hurt": ["Play_Hoshiguma_CN_032"],
    "pilot_inspired": ["Play_Hoshiguma_CN_029"],
    "pilot_wakes": ["Play_Hoshiguma_CN_024"],
    "pvp_start": ["Play_Hoshiguma_CN_031"],
    "reserve": ["Play_Hoshiguma_CN_022"],
    "retreat": ["Play_Hoshiguma_CN_032"],
    "sensor_lock_onthem": ["Play_Hoshiguma_CN_024"],
    "sensor_lock_onus": ["Play_Hoshiguma_CN_030"],
    "sprint": ["Play_Hoshiguma_CN_029"],
    "support_used": ["Play_Hoshiguma_CN_030"],
    "target_alpha": ["Play_Hoshiguma_CN_025"],
    "target_dfa": ["Play_Hoshiguma_CN_027"],
    "target_fire": ["Play_Hoshiguma_CN_028"],
    "target_melee": ["Play_Hoshiguma_CN_026"],
    "target_missed": ["Play_Hoshiguma_CN_023"],
    "target_multi": ["Play_Hoshiguma_CN_028"],
    "target_rear": ["Play_Hoshiguma_CN_024"],
    "target_structure": ["Play_Hoshiguma_CN_027"],
    "turret_destroyed": ["Play_Hoshiguma_CN_026"],
    "warning_flank": ["Play_Hoshiguma_CN_031"],
    "weapon_lost_all": ["Play_Hoshiguma_CN_032"],
    "weapon_lost": ["Play_Hoshiguma_CN_031"]
  }
}